{
    "Abbc": [""],
    "AbbcBadge": [""],
    "AcalaNetwork": [""],
    "AcalaNetworkBadge": [""],
    "Achain": [""],
    "Adcoin": [""],
    "AidosKuneen": [""],
    "Aion": [""],
    "AionBadge": [""],
    "Algorand": [""],
    "AlgorandBadge": [""],
    "Alqo": [""],
    "AlqoBadge": [""],
    "AppCoins": [""],
    "AppCoinsBadge": [""],
    "Avalanche": [""],
    "AvalancheBadge": [""],
    "BLThreeP": ["exchange"],
    "BLThreePBadge": ["exchange"],
    "Bancor": [""],
    "BancorBadge": [""],
    "BasicAttentionToken": [""],
    "BasicAttentionTokenBadge": [""],
    "Binance": ["exchange"],
    "BinanceBadge": ["exchange"],
    "BinanceSmartChain": [""],
    "BinanceSmartChainBadge": [""],
    "BinanceUsd": [""],
    "BinanceUsdBadge": [""],
    "BitMart": ["exchange"],
    "BitMartBadge": ["exchange"],
    "Bitbank": ["exchange"],
    "BitbankBadge": ["exchange"],
    "Bitcoin": [""],
    "BitcoinBadge": [""],
    "BitcoinCash": [""],
    "BitcoinCashBadge": [""],
    "BitcoinWrapped": [""],
    "Bitfinex": ["exchange"],
    "BitfinexBadge": ["exchange"],
    "Bitflyer": ["exchange"],
    "BitflyerBadge": ["exchange"],
    "Bithumb": ["exchange"],
    "BithumbBadge": ["exchange"],
    "Bitstamp": ["exchange"],
    "BitstampBadge": ["exchange"],
    "Bittrex": ["exchange"],
    "BittrexBadge": ["exchange"],
    "Bitvavo": ["exchange"],
    "BitvavoBadge": ["exchange"],
    "Blackmoon": [""],
    "BlockFi": [""],
    "BlockFiBadge": [""],
    "Brave": [""],
    "BraveBadge": [""],
    "Cardano": [""],
    "CardanoBadge": [""],
    "Cex": ["exchange"],
    "CexBadge": ["exchange"],
    "Chainlink": [""],
    "ChainlinkBadge": [""],
    "ChangellyPro": ["exchange"],
    "ChangellyProBadge": ["exchange"],
    "CoinDesk": ["exchange"],
    "CoinDeskBadge": ["exchange"],
    "CoinGecko": [""],
    "CoinGeckoBadge": [""],
    "CoinMarketCap": [""],
    "CoinMarketCapBadge": [""],
    "Coinone": ["exchange"],
    "CoinoneBadge": ["exchange"],
    "Compound": ["exchange"],
    "CompoundBadge": ["exchange"],
    "Consensys": [""],
    "ConsensysBadge": [""],
    "ConsensysCodefi": [""],
    "ConsensysCodefiBadge": [""],
    "Cosmos": [""],
    "CosmosBadge": [""],
    "Cream": [""],
    "CreamBadge": [""],
    "CryptoCom": ["exchange"],
    "CryptoComBadge": ["exchange"],
    "CurrencyCom": ["exchange"],
    "CurrencyComBadge": ["exchange"],
    "Curve": ["exchange"],
    "CurveBadge": ["exchange"],
    "Dash": [""],
    "DashBadge": [""],
    "Decentraland": [""],
    "Digibyte": [""],
    "Digifinex": ["exchange"],
    "DigifinexBadge": ["exchange"],
    "DockDock": [""],
    "Dogecoin": [""],
    "DogecoinBadge": [""],
    "Ens": [""],
    "EnsBadge": [""],
    "Eosio": [""],
    "EosioBadge": [""],
    "Ethereum": [""],
    "EthereumBadge": [""],
    "EthereumClassic": [""],
    "EthereumClassicBadge": [""],
    "Etoro": ["exchange"],
    "EtoroBadge": ["exchange"],
    "FileCoin": [""],
    "FileCoinBadge": [""],
    "Flux": [""],
    "FluxBadge": [""],
    "Ftx": ["exchange"],
    "FtxBadge": ["exchange"],
    "GateIo": ["exchange"],
    "GateIoBadge": ["exchange"],
    "Gemini": ["exchange"],
    "GeminiBadge": ["exchange"],
    "Gitcoin": [""],
    "GitcoinBadge": [""],
    "Harmony": [""],
    "Hedera": [""],
    "HederaBadge": [""],
    "Horizen": [""],
    "HorizenBadge": [""],
    "HuobiGlobal": ["exchange"],
    "HuobiGlobalBadge": ["exchange"],
    "Indodax": ["exchange"],
    "IndodaxBadge": ["exchange"],
    "Infura": [""],
    "InfuraBadge": [""],
    "Injective": [""],
    "InjectiveBadge": [""],
    "Iota": [""],
    "IotaBadge": [""],
    "KeeperDao": [""],
    "KeeperDaoBadge": [""],
    "Kraken": ["exchange"],
    "KrakenBadge": ["exchange"],
    "Kucoin": ["exchange"],
    "KucoinBadge": ["exchange"],
    "KusamaBadge": [""],
    "Liquid": ["exchange"],
    "LiquidBadge": ["exchange"],
    "Litecoin": [""],
    "LitecoinBadge": [""],
    "LivePeer": [""],
    "LivePeerBadge": [""],
    "Luno": ["exchange"],
    "LunoBadge": ["exchange"],
    "Meetone": [""],
    "MetaMask": [""],
    "MetaMaskBadge": [""],
    "Monero": [""],
    "MoneroBadge": [""],
    "MyCrypto": [""],
    "MyCryptoBadge": [""],
    "Nem": [""],
    "NemBadge": [""],
    "Nexo": [""],
    "NexoBadge": [""],
    "Okex": ["exchange"],
    "OkexBadge": ["exchange"],
    "OneInch": [""],
    "OneInchBadge": [""],
    "OpenDao": [""],
    "OpenDaoBadge": [""],
    "Origin": [""],
    "OriginBadge": [""],
    "Paxos": [""],
    "PaxosBadge": [""],
    "Pillar": [""],
    "PillarBadge": [""],
    "Polkadot": [""],
    "PolkadotBadge": [""],
    "Poloniex": ["exchange"],
    "PoloniexBadge": ["exchange"],
    "Polygon": [""],
    "PolygonBadge": [""],
    "Quorum": [""],
    "QuorumBadge": [""],
    "ShibaInu": [""],
    "ShibaInuBadge": [""],
    "Solana": [""],
    "SolanaBadge": [""],
    "Stacks": [""],
    "StacksBadge": [""],
    "Stakenet": [""],
    "StakenetBadge": [""],
    "Stellar": [""],
    "StellarBadge": [""],
    "SushiSwap": ["exchange"],
    "SushiSwapBadge": ["exchange"],
    "SwarmCity": [""],
    "SwarmCityBadge": [""],
    "Terarium": [""],
    "TerariumBadge": [""],
    "Terra": [""],
    "TerraBadge": [""],
    "Tether": [""],
    "TetherBadge": [""],
    "TetherGold": [""],
    "TetherGoldBadge": [""],
    "Tezos": [""],
    "TezosBadge": [""],
    "Trezor": [""],
    "TrezorBadge": [""],
    "Tron": [""],
    "TronBadge": [""],
    "Truffle": [""],
    "TruffleBadge": [""],
    "Uniswap": ["exchange"],
    "UniswapBadge": ["exchange"],
    "UnstoppableDomains": [""],
    "UnstoppableDomainsBadge": [""],
    "Upbit": ["exchange"],
    "UpbitBadge": ["exchange"],
    "Varen": [""],
    "VarenBadge": [""],
    "VeChain": [""],
    "VeChainBadge": [""],
    "WazirX": ["exchange"],
    "WazirXBadge": ["exchange"],
    "XMark": [""],
    "XMarkBadge": [""],
    "Xensor": [""],
    "XensorBadge": [""],
    "Xmx": [""],
    "XmxBadge": [""],
    "ZCash": [""],
    "ZCashBadge": [""],
    "Zapper": [""],
    "ZapperBadge": [""],
    "Zb": [""],
    "ZbBadge": [""],
    "Zcoin": [""],
    "ZcoinBadge": [""],
    "ZebPay": [""],
    "ZebPayBadge": [""],
    "ZeroCollateralDai": [""],
    "ZeroCollateralDaiBadge": [""],
    "ZeroX": [""],
    "ZeroXBadge": [""],
    "Zilliqa": [""],
    "ZilliqaBadge": [""]
}
